fq/__init__.py
fq/charts.py
fq/cli.py
linefreq-0.2.2.dist-info/entry_points.txt
linefreq-0.2.2.dist-info/WHEEL
linefreq-0.2.2.dist-info/METADATA
linefreq-0.2.2.dist-info/RECORD
