Metadata-Version: 2.1
Name: linefreq
Version: 0.2.2
Summary: a real time line frequency utility
Home-page: https://github.com/redraw/fq
License: MIT
Author: redraw
Author-email: redraw@sdf.org
Requires-Python: >=3.7,<4
Classifier: License :: OSI Approved :: MIT License
Classifier: Programming Language :: Python :: 3
Classifier: Programming Language :: Python :: 3.10
Classifier: Programming Language :: Python :: 3.7
Classifier: Programming Language :: Python :: 3.8
Classifier: Programming Language :: Python :: 3.9
Requires-Dist: rich (>=12.0.0,<13.0.0)
Requires-Dist: termplotlib (>=0.3.9,<0.4.0)
Project-URL: Repository, https://github.com/redraw/fq
